{"id":"258800","date":"2025-03-04","name":"League Standard | Season 11 (6/12)","format":"standard","standings":[{"rank":1,"player":{"display_name":"Zubovich Valery","id":"aspelled"},"points":12,"deck":{"archetype":"Golgari Obliterator","colors":"BG","type":"Midrange"},"rounds":[{"vs":9,"record":"win","res":1},{"vs":12,"record":"win","res":1},{"vs":3,"record":"win","res":1},{"vs":2,"record":"win","res":1}]},{"rank":2,"player":{"display_name":"Raptunovich Aleksei","id":"alex88"},"points":9,"deck":{"archetype":"Boros Aggro","colors":"WR","type":"Aggro"},"rounds":[{"vs":11,"record":"win","res":1},{"vs":4,"record":"win","res":1},{"vs":6,"record":"win","res":1},{"vs":1,"record":"lose","res":-1}]},{"rank":3,"player":{"display_name":"Snytko Egor","id":"warded-bye"},"points":9,"deck":{"archetype":"Rakdos Sacrifice","colors":"BR","type":"Midrange"},"rounds":[{"vs":10,"record":"win","res":1},{"vs":8,"record":"win","res":1},{"vs":1,"record":"lose","res":-1},{"vs":7,"record":"win","res":1}]},{"rank":4,"player":{"display_name":"Kondibor Nikita","id":"k1ppy"},"points":9,"deck":{"archetype":"Mono-Red Aggro","colors":"R","type":"Aggro"},"rounds":[{"vs":5,"record":"win","res":1},{"vs":2,"record":"lose","res":-1},{"vs":13,"record":"win","res":1},{"vs":8,"record":"win","res":1}]},{"rank":5,"player":{"display_name":"Ihnatsik Yauheni","id":"mcrais"},"points":9,"deck":{"archetype":"Esper Oculus","colors":"WUB","type":"Midrange"},"rounds":[{"vs":4,"record":"lose","res":-1},{"vs":16,"record":"win","res":1},{"vs":14,"record":"win","res":1},{"vs":6,"record":"win","res":1}]},{"rank":6,"player":{"display_name":"Savchenko Oleg","id":"lspolegi"},"points":6,"deck":{"archetype":"Jeskai Oculus","colors":"WUR","type":"Midrange"},"rounds":[{"vs":7,"record":"win","res":1},{"vs":13,"record":"win","res":1},{"vs":2,"record":"lose","res":-1},{"vs":5,"record":"lose","res":-1}]},{"rank":7,"player":{"display_name":"Vorotinsky Vitaliy","id":"vorotinskyv"},"points":6,"deck":{"archetype":"Gruul Resonance","colors":"RG","type":"Aggro"},"rounds":[{"vs":6,"record":"lose","res":-1},{"vs":9,"record":"win","res":1},{"vs":10,"record":"win","res":1},{"vs":3,"record":"lose","res":-1}]},{"rank":8,"player":{"display_name":"Brozhat Rostislav","id":"brv"},"points":6,"deck":{"archetype":"Gruul Resonance","colors":"RG","type":"Aggro"},"rounds":[{"vs":14,"record":"win","res":1},{"vs":3,"record":"lose","res":-1},{"vs":12,"record":"win","res":1},{"vs":4,"record":"lose","res":-1}]},{"rank":9,"player":{"display_name":"Kolyshko Alexander","id":"aklshk"},"points":6,"deck":{"archetype":"Gruul Aggro","colors":"RG","type":"Aggro"},"rounds":[{"vs":1,"record":"lose","res":-1},{"vs":7,"record":"lose","res":-1},{"vs":16,"record":"win","res":1},{"vs":14,"record":"win","res":1}]},{"rank":10,"player":{"display_name":"Kokhan Roman","id":"romankohan14"},"points":6,"deck":{"archetype":"Gruul Aggro","colors":"RG","type":"Aggro"},"rounds":[{"vs":3,"record":"lose","res":-1},{"vs":15,"record":"win","res":1},{"vs":7,"record":"lose","res":-1},{"vs":12,"record":"win","res":1}]},{"rank":11,"player":{"display_name":"Chakhouski Vasili","id":"4exoffby"},"points":4,"deck":{"archetype":"Dimir Midrange","colors":"UB","type":"Midrange"},"rounds":[{"vs":2,"record":"lose","res":-1},{"vs":14,"record":"lose","res":-1},{"vs":15,"record":"draw","res":0},"bye"]},{"rank":12,"player":{"display_name":"Latkovich Nikita","id":"nicklatkovich"},"points":3,"deck":{"archetype":"Bant Poison","colors":"WUG","type":"Aggro"},"rounds":[{"vs":15,"record":"win","res":1},{"vs":1,"record":"lose","res":-1},{"vs":8,"record":"lose","res":-1},{"vs":10,"record":"lose","res":-1}]},{"rank":13,"player":{"display_name":"Burankou Aliaksei","id":"burial63"},"points":3,"deck":{"archetype":"Dimir Bounce","colors":"UB","type":"Midrange"},"rounds":[{"vs":16,"record":"win","res":1},{"vs":6,"record":"lose","res":-1},{"vs":4,"record":"lose","res":-1},null]},{"rank":14,"player":{"display_name":"Bondarchik Andrei","id":"omgprofunny"},"points":3,"deck":{"archetype":"Jeskai Oculus","colors":"WUR","type":"Midrange"},"rounds":[{"vs":8,"record":"lose","res":-1},{"vs":11,"record":"win","res":1},{"vs":5,"record":"lose","res":-1},{"vs":9,"record":"lose","res":-1}]},{"rank":15,"player":{"display_name":"Novikov Valentine","id":"azurenia"},"points":1,"deck":{"archetype":"Temur Beanstalk","colors":"URG","type":"Control"},"rounds":[{"vs":12,"record":"lose","res":-1},{"vs":10,"record":"lose","res":-1},{"vs":11,"record":"draw","res":0},null]},{"rank":16,"player":{"display_name":"Martseniuk Maksim","id":"qvertion"},"points":0,"deck":{"archetype":"Jeskai Oculus","colors":"WUR","type":"Midrange"},"rounds":[{"vs":13,"record":"lose","res":-1},{"vs":5,"record":"lose","res":-1},{"vs":9,"record":"lose","res":-1},null]}]}
