{"id":"362552","date":"2025-09-09","name":"Daily | Standard (09.09)","format":"standard","standings":[{"rank":1,"player":{"display_name":"Shagoiko Maxim","id":"very-bad-man"},"points":9,"deck":{"archetype":"Temur Landfall","colors":"URG","type":null},"match_record":"3-1-0","game_record":"6-5-0","rounds":[{"vs":4,"record":"2-1-0","res":1},{"vs":2,"record":"2-1-0","res":1},{"vs":3,"record":"0-2-0","res":-1},{"vs":5,"record":"2-1-0","res":1}]},{"rank":2,"player":{"display_name":"Ihnatsik Yauheni","id":"mcrais"},"points":9,"deck":{"archetype":"Izzet Vivi","colors":"UR","type":"Tempo"},"match_record":"3-1-0","game_record":"7-2-0","rounds":[{"vs":7,"record":"2-0-0","res":1},{"vs":1,"record":"1-2-0","res":-1},{"vs":6,"record":"2-0-0","res":1},{"vs":3,"record":"2-0-0","res":1}]},{"rank":3,"player":{"display_name":"Kondibor Nikita","id":"k1ppy"},"points":9,"deck":{"archetype":"Azorius Control","colors":"WU","type":"Control"},"match_record":"3-1-0","game_record":"6-3-0","rounds":[{"vs":8,"record":"2-0-0","res":1},{"vs":5,"record":"2-1-0","res":1},{"vs":1,"record":"2-0-0","res":1},{"vs":2,"record":"0-2-0","res":-1}]},{"rank":4,"player":{"display_name":"Snytko Egor","id":"egors"},"points":9,"deck":{"archetype":"Rakdos Sacrifice","colors":"BR","type":"Midrange"},"match_record":"3-1-0","game_record":"7-4-0","rounds":[{"vs":1,"record":"1-2-0","res":-1},{"vs":7,"record":"2-1-0","res":1},{"vs":5,"record":"2-1-0","res":1},"bye"]},{"rank":5,"player":{"display_name":"Martseniuk Maksim","id":"qvertion"},"points":3,"deck":{"archetype":"Temur Battlecrier","colors":"URG","type":"Combo"},"match_record":"1-3-0","game_record":"5-7-0","rounds":[{"vs":6,"record":"2-1-0","res":1},{"vs":3,"record":"1-2-0","res":-1},{"vs":4,"record":"1-2-0","res":-1},{"vs":1,"record":"1-2-0","res":-1}]},{"rank":6,"player":{"display_name":"Burankou Aliaksei","id":"burial63"},"points":3,"deck":{"archetype":"Rakdos Lizards","colors":"BR","type":"Aggro"},"match_record":"1-2-0","game_record":"3-4-0","rounds":[{"vs":5,"record":"1-2-0","res":-1},{"vs":8,"record":"2-0-0","res":1},{"vs":2,"record":"0-2-0","res":-1},null]},{"rank":7,"player":{"display_name":"Kokhan Roman","id":"romankohan14"},"points":0,"deck":{"archetype":"Dimir Midrange","colors":"UB","type":"Midrange"},"match_record":"0-2-0","game_record":"1-4-0","rounds":[{"vs":2,"record":"0-2-0","res":-1},{"vs":4,"record":"1-2-0","res":-1},null,null]},{"rank":8,"player":{"display_name":"Novikov Valentine","id":"azurenia"},"points":0,"deck":{"archetype":"Orzhov Ketramose","colors":"WB","type":"Midrange"},"match_record":"0-2-0","game_record":"0-4-0","rounds":[{"vs":3,"record":"0-2-0","res":-1},{"vs":6,"record":"0-2-0","res":-1},null,null]}]}
