{"id":"407488","date":"2026-02-24","name":"Spring League 2026 | Standard #2/12","format":"standard","standings":[{"rank":1,"player":{"display_name":"Shagoiko Maxim","id":"very-bad-man"},"points":9,"match_record":"3-1-0","game_record":"6-3-0","rounds":[{"vs":2,"record":"2-1-0","res":1},{"vs":3,"record":"2-0-0","res":1},{"vs":4,"record":"2-0-0","res":1},{"vs":2,"record":"0-2-0","res":-1}]},{"rank":2,"player":{"display_name":"Krykun Damian","id":"damk6"},"points":6,"match_record":"2-2-0","game_record":"5-5-0","rounds":[{"vs":1,"record":"1-2-0","res":-1},{"vs":4,"record":"2-1-0","res":1},{"vs":3,"record":"0-2-0","res":-1},{"vs":1,"record":"2-0-0","res":1}]},{"rank":3,"player":{"display_name":"Brozhat Rostislav","id":"brv"},"points":6,"match_record":"2-2-0","game_record":"5-4-0","rounds":[{"vs":5,"record":"2-0-0","res":1},{"vs":1,"record":"0-2-0","res":-1},{"vs":2,"record":"2-0-0","res":1},{"vs":4,"record":"1-2-0","res":-1}]},{"rank":4,"player":{"display_name":"Moiseenko Pavel","id":"ykcyc"},"points":6,"match_record":"2-2-0","game_record":"5-5-0","rounds":["bye",{"vs":2,"record":"1-2-0","res":-1},{"vs":1,"record":"0-2-0","res":-1},{"vs":3,"record":"2-1-0","res":1}]},{"rank":5,"player":{"display_name":"Fando Evgeniy","id":"fondue"},"points":3,"match_record":"1-1-0","game_record":"2-2-0","rounds":[{"vs":3,"record":"0-2-0","res":-1},"bye",null,null]}]}
