{"id":"424084","date":"2026-05-02","name":"★★★ Big Magic Weekend | Spring 2026 | Pioneer","format":"pioneer","standings":[{"rank":1,"player":{"display_name":"Shagoiko Maxim","id":"very-bad-man"},"points":6,"deck":{"archetype":"Rakdos Midrange","colors":"BR","type":"Midrange"},"match_record":"4-1-0","game_record":"9-6-0","rounds":[{"vs":5,"record":"1-2-0","res":-1},{"vs":7,"record":"2-1-0","res":1},{"vs":6,"record":"2-1-0","res":1},{"vs":3,"record":"2-1-0","res":1},{"vs":2,"record":"2-1-0","res":1}]},{"rank":2,"player":{"display_name":"Krapivnitsky Gleb","id":"glebk"},"points":6,"deck":{"archetype":"Mono-Red Aggro","colors":"R","type":"Aggro"},"match_record":"3-2-0","game_record":"7-4-0","rounds":["bye",{"vs":6,"record":"2-0-0","res":1},{"vs":3,"record":"0-2-0","res":-1},{"vs":4,"record":"2-0-0","res":1},{"vs":1,"record":"1-2-0","res":-1}]},{"rank":3,"player":{"display_name":"Latkovich Nikita","id":"nicklatkovich"},"points":9,"deck":{"archetype":"Sultai Scapeshift","colors":"UBG","type":"Combo"},"match_record":"3-1-0","game_record":"7-2-0","rounds":[{"vs":4,"record":"2-0-0","res":1},{"vs":5,"record":"2-0-0","res":1},{"vs":2,"record":"2-0-0","res":1},{"vs":1,"record":"1-2-0","res":-1},null]},{"rank":4,"player":{"display_name":"Sarvira Mihail","id":"emera1d"},"points":6,"deck":{"archetype":"Izzet Phoenix","colors":"UR","type":"Tempo"},"match_record":"2-2-0","game_record":"4-5-0","rounds":[{"vs":3,"record":"0-2-0","res":-1},"bye",{"vs":5,"record":"2-1-0","res":1},{"vs":2,"record":"0-2-0","res":-1},null]},{"rank":5,"player":{"display_name":"Paulouski Tsimafei","id":"ispinyouround"},"points":3,"deck":{"archetype":"Rakdos Aggro","colors":"BR","type":"Aggro"},"match_record":"1-2-0","game_record":"3-5-0","rounds":[{"vs":1,"record":"2-1-0","res":1},{"vs":3,"record":"0-2-0","res":-1},{"vs":4,"record":"1-2-0","res":-1},null,null]},{"rank":6,"player":{"display_name":"Plisko Ihar","id":"4onoki"},"points":3,"deck":{"archetype":"Esper Bounce","colors":"WUB","type":"Midrange"},"match_record":"1-2-0","game_record":"3-4-0","rounds":[{"vs":7,"record":"2-0-0","res":1},{"vs":2,"record":"0-2-0","res":-1},{"vs":1,"record":"1-2-0","res":-1},null,null]},{"rank":7,"player":{"display_name":"Kryshkavets Egor","id":"damingez"},"points":3,"deck":{"archetype":"Rakdos Midrange","colors":"BR","type":"Midrange"},"match_record":"1-2-0","game_record":"3-4-0","rounds":[{"vs":6,"record":"0-2-0","res":-1},{"vs":1,"record":"1-2-0","res":-1},"bye",null,null]}]}
