{"id":"trios250713","date":"2025-07-13","name":"Special Event: Trios (13.07.25)","format":"trios","standings":[{"rank":1,"player":{"display_name":"Raptunovich Aleksei","id":"alex88"},"points":12,"deck":{"archetype":"Mono-Red Aggro","colors":"R","type":"Aggro"},"format":"pioneer","rounds":[{"vs":7,"record":"2-0-0","res":1,"teamWin":true},{"vs":5,"record":"2-0-0","res":1,"teamWin":true},{"vs":2,"record":"2-0-0","res":1,"teamWin":true},null,null,{"vs":2,"record":"2-1-0","res":1,"teamWin":true}]},{"rank":1,"player":{"display_name":"Kokhan Roman","id":"romankohan14"},"points":12,"deck":{"archetype":"Dimir Midrange","colors":"UB","type":"Midrange"},"format":"standard","rounds":[{"vs":7,"record":"2-0-0","res":1,"teamWin":true},{"vs":5,"record":"0-2-0","res":-1,"teamWin":true},{"vs":2,"record":"2-0-0","res":1,"teamWin":true},null,null,{"vs":2,"record":"2-1-0","res":1,"teamWin":true}]},{"rank":1,"player":{"display_name":"Charniauski Mikita","id":"tanti"},"points":12,"deck":{"archetype":"Domain Control","colors":"WUBRG","type":"Control"},"format":"legacy","rounds":[{"vs":7,"record":"2-0-0","res":1,"teamWin":true},{"vs":5,"record":"2-0-0","res":1,"teamWin":true},{"vs":2,"record":"1-1-0","res":0,"teamWin":true,"notFinished":true},null,null,{"vs":2,"record":"lose","res":-1,"teamWin":true}]},{"rank":2,"player":{"display_name":"Trofimov Valera","id":"trov1"},"points":9,"deck":{"archetype":"Niv to Light","colors":"WUBRG","type":"Control"},"format":"pioneer","rounds":[{"vs":8,"record":"win","res":1,"teamWin":true},{"vs":4,"record":"2-0-0","res":1,"teamWin":true},{"vs":1,"record":"0-2-0","res":-1,"teamWin":false},null,{"vs":3,"record":"2-0-0","res":1,"teamWin":true},{"vs":1,"record":"1-2-0","res":-1,"teamWin":false}]},{"rank":2,"player":{"display_name":"Zubovich Valery","id":"aspelled"},"points":9,"deck":{"archetype":"Jeskai Oculus","colors":"WUR","type":"Midrange"},"format":"standard","rounds":[{"vs":8,"record":"win","res":1,"teamWin":true},{"vs":4,"record":"2-0-0","res":1,"teamWin":true},{"vs":1,"record":"0-2-0","res":-1,"teamWin":false},null,{"vs":3,"record":"lose","res":-1,"teamWin":true},{"vs":1,"record":"1-2-0","res":-1,"teamWin":false}]},{"rank":2,"player":{"display_name":"Rapanovich Yauhen","id":"farsmac"},"points":9,"deck":{"archetype":"Colorless Cloudpost","colors":"c","type":"Combo"},"format":"legacy","rounds":[{"vs":8,"record":"win","res":1,"teamWin":true},{"vs":4,"record":"1-2-0","res":-1,"teamWin":true},{"vs":1,"record":"1-1-0","res":0,"teamWin":false,"notFinished":true},null,{"vs":3,"record":"win","res":1,"teamWin":true},{"vs":1,"record":"win","res":1,"teamWin":false}]},{"rank":3,"player":{"display_name":"Ihnatsik Yauheni","id":"mcrais"},"points":9,"deck":{"archetype":"Orzhov Control","colors":"WB","type":"Control"},"format":"pioneer","rounds":[{"vs":4,"record":"1-2-0","res":-1,"teamWin":false},{"vs":8,"record":"-","res":0,"teamWin":true,"notFinished":true},{"vs":5,"record":"1-2-0","res":-1,"teamWin":true},{"vs":4,"record":"0-1-0","res":0,"teamWin":true,"notFinished":true},{"vs":2,"record":"0-2-0","res":-1,"teamWin":false},null]},{"rank":3,"player":{"display_name":"Kryshkavets Egor","id":"damingez"},"points":9,"deck":{"archetype":"Golgari Midrange","colors":"BG","type":"Midrange"},"format":"standard","rounds":[{"vs":4,"record":"1-2-0","res":-1,"teamWin":false},{"vs":8,"record":"-","res":0,"teamWin":true,"notFinished":true},{"vs":5,"record":"2-1-0","res":1,"teamWin":true},{"vs":4,"record":"2-0-0","res":1,"teamWin":true},{"vs":2,"record":"win","res":1,"teamWin":false},null]},{"rank":3,"player":{"display_name":"Yushkevich Egor","id":"melamasta"},"points":9,"deck":{"archetype":"Mississippi River","colors":"URG","type":"Combo"},"format":"legacy","rounds":[{"vs":4,"record":"1-2-0","res":-1,"teamWin":false},{"vs":8,"record":"-","res":0,"teamWin":true,"notFinished":true},{"vs":5,"record":"2-0-0","res":1,"teamWin":true},{"vs":4,"record":"2-0-0","res":1,"teamWin":true},{"vs":2,"record":"lose","res":-1,"teamWin":false},null]},{"rank":4,"player":{"display_name":"Chuyanau Dzianis","id":"anklden"},"points":6,"deck":{"archetype":"Niv to Light","colors":"WUBRG","type":"Control"},"format":"pioneer","rounds":[{"vs":3,"record":"2-1-0","res":1,"teamWin":true},{"vs":2,"record":"0-2-0","res":-1,"teamWin":false},{"vs":6,"record":"2-0-0","res":1,"teamWin":true},{"vs":3,"record":"0-1-0","res":0,"teamWin":false,"notFinished":true},null,null]},{"rank":4,"player":{"display_name":"Brozhat Rostislav","id":"brv"},"points":6,"deck":{"archetype":"Boros Convoke","colors":"WR","type":"Aggro"},"format":"standard","rounds":[{"vs":3,"record":"2-1-0","res":1,"teamWin":true},{"vs":2,"record":"0-2-0","res":-1,"teamWin":false},{"vs":6,"record":"2-1-0","res":1,"teamWin":true},{"vs":3,"record":"0-2-0","res":-1,"teamWin":false},null,null]},{"rank":4,"player":{"display_name":"Latkovich Nikita","id":"nicklatkovich"},"points":6,"deck":{"archetype":"Mono-Blue Oracle","colors":"U","type":"Combo"},"format":"legacy","rounds":[{"vs":3,"record":"2-1-0","res":1,"teamWin":true},{"vs":2,"record":"2-1-0","res":1,"teamWin":false},{"vs":6,"record":"1-2-0","res":-1,"teamWin":true},{"vs":3,"record":"0-2-0","res":-1,"teamWin":false},null,null]},{"rank":5,"player":{"display_name":"Shagoiko Maxim","id":"very-bad-man"},"points":3,"deck":{"archetype":"Rakdos Midrange","colors":"BR","type":"Midrange"},"format":"pioneer","rounds":[{"vs":6,"record":"1-1-0","res":0,"teamWin":true,"notFinished":true},{"vs":1,"record":"0-2-0","res":-1,"teamWin":false},{"vs":3,"record":"2-1-0","res":1,"teamWin":false},null,null,null]},{"rank":5,"player":{"display_name":"Bondarchik Andrei","id":"omgprofunny"},"points":3,"deck":{"archetype":"Dimir Midrange","colors":"UB","type":"Midrange"},"format":"standard","rounds":[{"vs":6,"record":"2-0-0","res":1,"teamWin":true},{"vs":1,"record":"2-0-0","res":1,"teamWin":false},{"vs":3,"record":"1-2-0","res":-1,"teamWin":false},null,null,null]},{"rank":5,"player":{"display_name":"Bandarchyk Anton","id":"summie"},"points":3,"deck":{"archetype":"Domain Control","colors":"WUBRG","type":"Control"},"format":"legacy","rounds":[{"vs":6,"record":"2-1-0","res":1,"teamWin":true},{"vs":1,"record":"0-2-0","res":-1,"teamWin":false},{"vs":3,"record":"0-2-0","res":-1,"teamWin":false},null,null,null]},{"rank":6,"player":{"display_name":"Duzhev Ivan","id":"gerber2000"},"points":3,"deck":{"archetype":"Jund Sacrifice","colors":"BRG","type":"Combo"},"format":"pioneer","rounds":[{"vs":5,"record":"1-1-0","res":0,"teamWin":false,"notFinished":true},{"vs":7,"record":"2-0-0","res":1,"teamWin":true},{"vs":4,"record":"0-2-0","res":-1,"teamWin":false},null,null,null]},{"rank":6,"player":{"display_name":"Buslavsky Alexander","id":"shadowest"},"points":3,"deck":{"archetype":"Mono-Black Midrange","colors":"B","type":"Midrange"},"format":"standard","rounds":[{"vs":5,"record":"0-2-0","res":-1,"teamWin":false},{"vs":7,"record":"2-0-0","res":1,"teamWin":true},{"vs":4,"record":"1-2-0","res":-1,"teamWin":false},null,null,null]},{"rank":6,"player":{"display_name":"Kolyshko Alexander","id":"aklshk"},"points":3,"deck":{"archetype":"Azorius Dreadnought","colors":"WU","type":null},"format":"legacy","rounds":[{"vs":5,"record":"1-2-0","res":-1,"teamWin":false},{"vs":7,"record":"2-0-0","res":1,"teamWin":true},{"vs":4,"record":"2-1-0","res":1,"teamWin":false},null,null,null]},{"rank":7,"player":{"display_name":"Martseniuk Maksim","id":"qvertion"},"points":0,"deck":{"archetype":"Mono-Red Aggro","colors":"R","type":"Aggro"},"format":"pioneer","rounds":[{"vs":1,"record":"0-2-0","res":-1,"teamWin":false},{"vs":6,"record":"0-2-0","res":-1,"teamWin":false},null,null,null,null]},{"rank":7,"player":{"display_name":"Novikov Valentine","id":"azurenia"},"points":0,"deck":{"archetype":"Dimir Midrange","colors":"UB","type":"Midrange"},"format":"standard","rounds":[{"vs":1,"record":"0-2-0","res":-1,"teamWin":false},{"vs":6,"record":"0-2-0","res":-1,"teamWin":false},null,null,null,null]},{"rank":7,"player":{"display_name":"Kondibor Nikita","id":"k1ppy"},"points":0,"deck":{"archetype":"Mono-Red Prison","colors":"R","type":null},"format":"legacy","rounds":[{"vs":1,"record":"0-2-0","res":-1,"teamWin":false},{"vs":6,"record":"0-2-0","res":-1,"teamWin":false},null,null,null,null]},{"rank":8,"player":{"display_name":"Krapivnitsky Gleb","id":"glebk"},"points":0,"deck":{"archetype":"Mono-Red Aggro","colors":"R","type":"Aggro"},"format":"pioneer","rounds":[{"vs":2,"record":"lose","res":-1,"teamWin":false},{"vs":3,"record":"-","res":0,"teamWin":false,"notFinished":true},null,null,null,null]},{"rank":8,"player":{"display_name":"Lashkin Ilya","id":"soxa"},"points":0,"deck":{"archetype":"Azorius Enchantments","colors":"WU","type":"Aggro"},"format":"standard","rounds":[{"vs":2,"record":"lose","res":-1,"teamWin":false},{"vs":3,"record":"-","res":0,"teamWin":false,"notFinished":true},null,null,null,null]},{"rank":8,"player":{"display_name":"Sutko Artem","id":"sutko"},"points":0,"deck":{"archetype":"Mono-Blue Omni-Tell","colors":"U","type":"Combo"},"format":"legacy","rounds":[{"vs":2,"record":"lose","res":-1,"teamWin":false},{"vs":3,"record":"-","res":0,"teamWin":false,"notFinished":true},null,null,null,null]}]}
